py2dist/__init__.py
py2dist/__main__.py
py2dist/cli.py
py2dist/compiler.py
py2dist/template.py
py2dist-0.1.6.dist-info/METADATA
py2dist-0.1.6.dist-info/WHEEL
py2dist-0.1.6.dist-info/entry_points.txt
py2dist-0.1.6.dist-info/licenses/LICENSE
py2dist-0.1.6.dist-info/RECORD
